[
  {
    "policy_name": "ICICI Future Perfect   Brochure",
    "source": "ICICI Future Perfect - Brochure.pdf",
    "policy_type": "unknown"
  },
  {
    "policy_name": "ICICI Pru iProtect Smart",
    "source": "ICICI Pru iProtect Smart.pdf",
    "policy_type": "unknown"
  },
  {
    "policy_name": "ICICI Pru LifeTime Classic Brochure Final",
    "source": "ICICI_Pru_LifeTime_Classic_Brochure_Final.pdf",
    "policy_type": "unknown"
  },
  {
    "policy_name": "ICICI Pru Sukh Samruddhi Brochure",
    "source": "ICICI_Pru_Sukh-Samruddhi_Brochure.pdf",
    "policy_type": "unknown"
  }
]